dcd_py_util/__init__.py
dcd_py_util/encryption.py
dcd_py_util/logger.py
dcd_py_util/prefs_config.py
dcd_py_util-0.0.4.dist-info/LICENSE
dcd_py_util-0.0.4.dist-info/METADATA
dcd_py_util-0.0.4.dist-info/WHEEL
dcd_py_util-0.0.4.dist-info/top_level.txt
dcd_py_util-0.0.4.dist-info/RECORD
