Metadata-Version: 2.1
Name: dcd-py-util
Version: 0.0.4
Summary: Module that brings together useful tools for Python applications.
Author-email: Daniel Carvalho Dias <daniel.dias@gmail.com>
Project-URL: Homepage, https://github.com/danielcdias/dcd_py_util
Project-URL: Bug Tracker, https://github.com/danielcdias/dcd_py_util/issues
Classifier: Programming Language :: Python :: 3
Classifier: License :: OSI Approved :: MIT License
Classifier: Operating System :: OS Independent
Requires-Python: >=3.10
License-File: LICENSE
